radar5/__config__.py
radar5/__init__.py
radar5/radar5.pyd
radar5/.libs/libradar5.LEB5BDOKMSC3LX6XYZFWM4XIW5CFHCCY.gfortran-win_amd64.dll
radar5-0.1.dist-info/LICENSE.txt
radar5-0.1.dist-info/METADATA
radar5-0.1.dist-info/RECORD
radar5-0.1.dist-info/WHEEL
radar5-0.1.dist-info/top_level.txt
