Metadata-Version: 2.1
Name: radar5
Version: 0.1
Summary: Python wrapper of the RADAR5 solver for delayed differential equations (DDE).
Home-page: https://github.com/thoduv/pyradar5
Author: Aurélien Thorette
Author-email: thoduv@free.fr
License: LGPL
Keywords: delay,differential equation,numerical,radar5,dde,integration,mathematics
Platform: UNKNOWN
Classifier: Topic :: Scientific/Engineering
Classifier: Programming Language :: Python :: 3
Classifier: Programming Language :: Python :: 2
Classifier: Programming Language :: Python :: Implementation :: CPython
Classifier: License :: OSI Approved :: GNU Library or Lesser General Public License (LGPL)
Classifier: Operating System :: Microsoft :: Windows
Classifier: Operating System :: POSIX
Classifier: Intended Audience :: Science/Research
Classifier: Development Status :: 4 - Beta
Requires-Dist: numpy
